tedriver/__init__.py
tedriver/example.py
tedriver-0.0.1.dist-info/LICENSE
tedriver-0.0.1.dist-info/METADATA
tedriver-0.0.1.dist-info/WHEEL
tedriver-0.0.1.dist-info/top_level.txt
tedriver-0.0.1.dist-info/RECORD
